{
    "manufacturers": {
        "Eurolite": {
            "name": "Eurolite"
        }
    },
    "fixtures": [
        {
            "manufacturer": "Eurolite",
            "name": "LED SCY-100 RGBW DMX",
            "type": "Effect",
            "physical": {
                "dimensions": [460, 155, 355],
                "weight": 4,
                "power": 25,
                "DMXconnector": "3-pin",
                "bulb": {
                    "type": "LED"
                },
                "lens": {
                    "name": "Other",
                    "degreesMinMax": [15, 15]
                },
                "focus": {
                    "type": "Fixed"
                }
            },
            "availableChannels": {
                "Lens 1": {
                    "type": "MultiColor",
                    "capabilities": [
                        {
                            "range": [0, 10],
                            "name": "Off"
                        },
                        {
                            "range": [11, 24],
                            "name": "Red on",
                            "color": "#ff0000"
                        },
                        {
                            "range": [25, 38],
                            "name": "Green on",
                            "color": "#00ff00"
                        },
                        {
                            "range": [39, 52],
                            "name": "Blue on",
                            "color": "#0000ff"
                        },
                        {
                            "range": [53, 66],
                            "name": "Group 1 white on",
                            "color": "#ffffff"
                        },
                        {
                            "range": [67, 80],
                            "name": "Group 2 white on",
                            "color": "#ffffff"
                        },
                        {
                            "range": [81, 94],
                            "name": "Group 3 white on",
                            "color": "#ffffff"
                        },
                        {
                            "range": [95, 108],
                            "name": "White on",
                            "color": "#ffffff"
                        },
                        {
                            "range": [109, 122],
                            "name": "Red and green on",
                            "color": "#ff0000",
                            "color2": "#00ff00"
                        },
                        {
                            "range": [123, 136],
                            "name": "Red and blue on",
                            "color": "#ff0000",
                            "color2": "#0000ff"
                        },
                        {
                            "range": [137, 150],
                            "name": "Green and blue on",
                            "color": "#00ff00",
                            "color2": "#0000ff"
                        },
                        {
                            "range": [151, 164],
                            "name": "Red and white on",
                            "color": "#ff0000",
                            "color2": "#ffffff"
                        },
                        {
                            "range": [165, 178],
                            "name": "Green and white on",
                            "color": "#00ff00",
                            "color2": "#ffffff"
                        },
                        {
                            "range": [179, 192],
                            "name": "Blue and white on",
                            "color": "#0000ff",
                            "color2": "#ffffff"
                        },
                        {
                            "range": [193, 206],
                            "name": "Red, green and blue on",
                            "color": "#ffffff"
                        },
                        {
                            "range": [207, 220],
                            "name": "Red, green and white on"
                        },
                        {
                            "range": [221, 234],
                            "name": "Green, blue and white on"
                        },
                        {
                            "range": [235, 255],
                            "name": "Red, green, blue and white on"
                        }
                    ]
                },
                "Lens 2": {
                    "type": "MultiColor",
                    "capabilities": [
                        {
                            "range": [0, 10],
                            "name": "Off"
                        },
                        {
                            "range": [11, 24],
                            "name": "Red on",
                            "color": "#ff0000"
                        },
                        {
                            "range": [25, 38],
                            "name": "Green on",
                            "color": "#00ff00"
                        },
                        {
                            "range": [39, 52],
                            "name": "Blue on",
                            "color": "#0000ff"
                        },
                        {
                            "range": [53, 66],
                            "name": "Group 1 white on",
                            "color": "#ffffff"
                        },
                        {
                            "range": [67, 80],
                            "name": "Group 2 white on",
                            "color": "#ffffff"
                        },
                        {
                            "range": [81, 94],
                            "name": "Group 3 white on",
                            "color": "#ffffff"
                        },
                        {
                            "range": [95, 108],
                            "name": "White on",
                            "color": "#ffffff"
                        },
                        {
                            "range": [109, 122],
                            "name": "Red and green on",
                            "color": "#ff0000",
                            "color2": "#00ff00"
                        },
                        {
                            "range": [123, 136],
                            "name": "Red and blue on",
                            "color": "#ff0000",
                            "color2": "#0000ff"
                        },
                        {
                            "range": [137, 150],
                            "name": "Green and blue on",
                            "color": "#00ff00",
                            "color2": "#0000ff"
                        },
                        {
                            "range": [151, 164],
                            "name": "Red and white on",
                            "color": "#ff0000",
                            "color2": "#ffffff"
                        },
                        {
                            "range": [165, 178],
                            "name": "Green and white on",
                            "color": "#00ff00",
                            "color2": "#ffffff"
                        },
                        {
                            "range": [179, 192],
                            "name": "Blue and white on",
                            "color": "#0000ff",
                            "color2": "#ffffff"
                        },
                        {
                            "range": [193, 206],
                            "name": "Red, green and blue on",
                            "color": "#ffffff"
                        },
                        {
                            "range": [207, 220],
                            "name": "Red, green and white on"
                        },
                        {
                            "range": [221, 234],
                            "name": "Green, blue and white on"
                        },
                        {
                            "range": [235, 255],
                            "name": "Red, green, blue and white on"
                        }
                    ]
                },
                "Lens 3": {
                    "type": "MultiColor",
                    "capabilities": [
                        {
                            "range": [0, 10],
                            "name": "Off"
                        },
                        {
                            "range": [11, 24],
                            "name": "Red on",
                            "color": "#ff0000"
                        },
                        {
                            "range": [25, 38],
                            "name": "Green on",
                            "color": "#00ff00"
                        },
                        {
                            "range": [39, 52],
                            "name": "Blue on",
                            "color": "#0000ff"
                        },
                        {
                            "range": [53, 66],
                            "name": "Group 1 white on",
                            "color": "#ffffff"
                        },
                        {
                            "range": [67, 80],
                            "name": "Group 2 white on",
                            "color": "#ffffff"
                        },
                        {
                            "range": [81, 94],
                            "name": "Group 3 white on",
                            "color": "#ffffff"
                        },
                        {
                            "range": [95, 108],
                            "name": "White on",
                            "color": "#ffffff"
                        },
                        {
                            "range": [109, 122],
                            "name": "Red and green on",
                            "color": "#ff0000",
                            "color2": "#00ff00"
                        },
                        {
                            "range": [123, 136],
                            "name": "Red and blue on",
                            "color": "#ff0000",
                            "color2": "#0000ff"
                        },
                        {
                            "range": [137, 150],
                            "name": "Green and blue on",
                            "color": "#00ff00",
                            "color2": "#0000ff"
                        },
                        {
                            "range": [151, 164],
                            "name": "Red and white on",
                            "color": "#ff0000",
                            "color2": "#ffffff"
                        },
                        {
                            "range": [165, 178],
                            "name": "Green and white on",
                            "color": "#00ff00",
                            "color2": "#ffffff"
                        },
                        {
                            "range": [179, 192],
                            "name": "Blue and white on",
                            "color": "#0000ff",
                            "color2": "#ffffff"
                        },
                        {
                            "range": [193, 206],
                            "name": "Red, green and blue on",
                            "color": "#ffffff"
                        },
                        {
                            "range": [207, 220],
                            "name": "Red, green and white on"
                        },
                        {
                            "range": [221, 234],
                            "name": "Green, blue and white on"
                        },
                        {
                            "range": [235, 255],
                            "name": "Red, green, blue and white on"
                        }
                    ]
                },
                "Lens 4": {
                    "type": "MultiColor",
                    "capabilities": [
                        {
                            "range": [0, 10],
                            "name": "Off"
                        },
                        {
                            "range": [11, 24],
                            "name": "Red on",
                            "color": "#ff0000"
                        },
                        {
                            "range": [25, 38],
                            "name": "Green on",
                            "color": "#00ff00"
                        },
                        {
                            "range": [39, 52],
                            "name": "Blue on",
                            "color": "#0000ff"
                        },
                        {
                            "range": [53, 66],
                            "name": "Group 1 white on",
                            "color": "#ffffff"
                        },
                        {
                            "range": [67, 80],
                            "name": "Group 2 white on",
                            "color": "#ffffff"
                        },
                        {
                            "range": [81, 94],
                            "name": "Group 3 white on",
                            "color": "#ffffff"
                        },
                        {
                            "range": [95, 108],
                            "name": "White on",
                            "color": "#ffffff"
                        },
                        {
                            "range": [109, 122],
                            "name": "Red and green on",
                            "color": "#ff0000",
                            "color2": "#00ff00"
                        },
                        {
                            "range": [123, 136],
                            "name": "Red and blue on",
                            "color": "#ff0000",
                            "color2": "#0000ff"
                        },
                        {
                            "range": [137, 150],
                            "name": "Green and blue on",
                            "color": "#00ff00",
                            "color2": "#0000ff"
                        },
                        {
                            "range": [151, 164],
                            "name": "Red and white on",
                            "color": "#ff0000",
                            "color2": "#ffffff"
                        },
                        {
                            "range": [165, 178],
                            "name": "Green and white on",
                            "color": "#00ff00",
                            "color2": "#ffffff"
                        },
                        {
                            "range": [179, 192],
                            "name": "Blue and white on",
                            "color": "#0000ff",
                            "color2": "#ffffff"
                        },
                        {
                            "range": [193, 206],
                            "name": "Red, green and blue on",
                            "color": "#ffffff"
                        },
                        {
                            "range": [207, 220],
                            "name": "Red, green and white on"
                        },
                        {
                            "range": [221, 234],
                            "name": "Green, blue and white on"
                        },
                        {
                            "range": [235, 255],
                            "name": "Red, green, blue and white on"
                        }
                    ]
                },
                "Lens 5": {
                    "type": "MultiColor",
                    "capabilities": [
                        {
                            "range": [0, 10],
                            "name": "Off"
                        },
                        {
                            "range": [11, 24],
                            "name": "Red on",
                            "color": "#ff0000"
                        },
                        {
                            "range": [25, 38],
                            "name": "Green on",
                            "color": "#00ff00"
                        },
                        {
                            "range": [39, 52],
                            "name": "Blue on",
                            "color": "#0000ff"
                        },
                        {
                            "range": [53, 66],
                            "name": "Group 1 white on",
                            "color": "#ffffff"
                        },
                        {
                            "range": [67, 80],
                            "name": "Group 2 white on",
                            "color": "#ffffff"
                        },
                        {
                            "range": [81, 94],
                            "name": "Group 3 white on",
                            "color": "#ffffff"
                        },
                        {
                            "range": [95, 108],
                            "name": "White on",
                            "color": "#ffffff"
                        },
                        {
                            "range": [109, 122],
                            "name": "Red and green on",
                            "color": "#ff0000",
                            "color2": "#00ff00"
                        },
                        {
                            "range": [123, 136],
                            "name": "Red and blue on",
                            "color": "#ff0000",
                            "color2": "#0000ff"
                        },
                        {
                            "range": [137, 150],
                            "name": "Green and blue on",
                            "color": "#00ff00",
                            "color2": "#0000ff"
                        },
                        {
                            "range": [151, 164],
                            "name": "Red and white on",
                            "color": "#ff0000",
                            "color2": "#ffffff"
                        },
                        {
                            "range": [165, 178],
                            "name": "Green and white on",
                            "color": "#00ff00",
                            "color2": "#ffffff"
                        },
                        {
                            "range": [179, 192],
                            "name": "Blue and white on",
                            "color": "#0000ff",
                            "color2": "#ffffff"
                        },
                        {
                            "range": [193, 206],
                            "name": "Red, green and blue on",
                            "color": "#ffffff"
                        },
                        {
                            "range": [207, 220],
                            "name": "Red, green and white on"
                        },
                        {
                            "range": [221, 234],
                            "name": "Green, blue and white on"
                        },
                        {
                            "range": [235, 255],
                            "name": "Red, green, blue and white on"
                        }
                    ]
                },
                "Lens 6": {
                    "type": "MultiColor",
                    "capabilities": [
                        {
                            "range": [0, 10],
                            "name": "Off"
                        },
                        {
                            "range": [11, 24],
                            "name": "Red on",
                            "color": "#ff0000"
                        },
                        {
                            "range": [25, 38],
                            "name": "Green on",
                            "color": "#00ff00"
                        },
                        {
                            "range": [39, 52],
                            "name": "Blue on",
                            "color": "#0000ff"
                        },
                        {
                            "range": [53, 66],
                            "name": "Group 1 white on",
                            "color": "#ffffff"
                        },
                        {
                            "range": [67, 80],
                            "name": "Group 2 white on",
                            "color": "#ffffff"
                        },
                        {
                            "range": [81, 94],
                            "name": "Group 3 white on",
                            "color": "#ffffff"
                        },
                        {
                            "range": [95, 108],
                            "name": "White on",
                            "color": "#ffffff"
                        },
                        {
                            "range": [109, 122],
                            "name": "Red and green on",
                            "color": "#ff0000",
                            "color2": "#00ff00"
                        },
                        {
                            "range": [123, 136],
                            "name": "Red and blue on",
                            "color": "#ff0000",
                            "color2": "#0000ff"
                        },
                        {
                            "range": [137, 150],
                            "name": "Green and blue on",
                            "color": "#00ff00",
                            "color2": "#0000ff"
                        },
                        {
                            "range": [151, 164],
                            "name": "Red and white on",
                            "color": "#ff0000",
                            "color2": "#ffffff"
                        },
                        {
                            "range": [165, 178],
                            "name": "Green and white on",
                            "color": "#00ff00",
                            "color2": "#ffffff"
                        },
                        {
                            "range": [179, 192],
                            "name": "Blue and white on",
                            "color": "#0000ff",
                            "color2": "#ffffff"
                        },
                        {
                            "range": [193, 206],
                            "name": "Red, green and blue on",
                            "color": "#ffffff"
                        },
                        {
                            "range": [207, 220],
                            "name": "Red, green and white on"
                        },
                        {
                            "range": [221, 234],
                            "name": "Green, blue and white on"
                        },
                        {
                            "range": [235, 255],
                            "name": "Red, green, blue and white on"
                        }
                    ]
                },
                "Lens 7": {
                    "type": "MultiColor",
                    "capabilities": [
                        {
                            "range": [0, 10],
                            "name": "Off"
                        },
                        {
                            "range": [11, 24],
                            "name": "Red on",
                            "color": "#ff0000"
                        },
                        {
                            "range": [25, 38],
                            "name": "Green on",
                            "color": "#00ff00"
                        },
                        {
                            "range": [39, 52],
                            "name": "Blue on",
                            "color": "#0000ff"
                        },
                        {
                            "range": [53, 66],
                            "name": "Group 1 white on",
                            "color": "#ffffff"
                        },
                        {
                            "range": [67, 80],
                            "name": "Group 2 white on",
                            "color": "#ffffff"
                        },
                        {
                            "range": [81, 94],
                            "name": "Group 3 white on",
                            "color": "#ffffff"
                        },
                        {
                            "range": [95, 108],
                            "name": "White on",
                            "color": "#ffffff"
                        },
                        {
                            "range": [109, 122],
                            "name": "Red and green on",
                            "color": "#ff0000",
                            "color2": "#00ff00"
                        },
                        {
                            "range": [123, 136],
                            "name": "Red and blue on",
                            "color": "#ff0000",
                            "color2": "#0000ff"
                        },
                        {
                            "range": [137, 150],
                            "name": "Green and blue on",
                            "color": "#00ff00",
                            "color2": "#0000ff"
                        },
                        {
                            "range": [151, 164],
                            "name": "Red and white on",
                            "color": "#ff0000",
                            "color2": "#ffffff"
                        },
                        {
                            "range": [165, 178],
                            "name": "Green and white on",
                            "color": "#00ff00",
                            "color2": "#ffffff"
                        },
                        {
                            "range": [179, 192],
                            "name": "Blue and white on",
                            "color": "#0000ff",
                            "color2": "#ffffff"
                        },
                        {
                            "range": [193, 206],
                            "name": "Red, green and blue on",
                            "color": "#ffffff"
                        },
                        {
                            "range": [207, 220],
                            "name": "Red, green and white on"
                        },
                        {
                            "range": [221, 234],
                            "name": "Green, blue and white on"
                        },
                        {
                            "range": [235, 255],
                            "name": "Red, green, blue and white on"
                        }
                    ]
                },
                "Strobe": {
                    "type": "Strobe",
                    "capabilities": [
                        {
                            "range": [0, 10],
                            "name": "Off"
                        },
                        {
                            "range": [11, 255],
                            "name": "Flash, with increasing speed"
                        }
                    ]
                },
                "Internal Programs, Auto Mode, Sound Controlled Mode": {
                    "type": "Maintenance",
                    "capabilities": [
                        {
                            "range": [0, 10],
                            "name": "Off"
                        },
                        {
                            "range": [11, 30],
                            "name": "Program 1"
                        },
                        {
                            "range": [31, 50],
                            "name": "Program 2"
                        },
                        {
                            "range": [51, 70],
                            "name": "Program 3"
                        },
                        {
                            "range": [71, 90],
                            "name": "Program 4"
                        },
                        {
                            "range": [91, 110],
                            "name": "Program 5"
                        },
                        {
                            "range": [111, 130],
                            "name": "Program 6"
                        },
                        {
                            "range": [131, 150],
                            "name": "Program 7"
                        },
                        {
                            "range": [151, 170],
                            "name": "Program 8"
                        },
                        {
                            "range": [171, 190],
                            "name": "Program 9"
                        },
                        {
                            "range": [191, 210],
                            "name": "Program 10"
                        },
                        {
                            "range": [211, 230],
                            "name": "Program 11"
                        },
                        {
                            "range": [231, 250],
                            "name": "Auto Mode: Internal Programs"
                        },
                        {
                            "range": [251, 255],
                            "name": "Sound Controlled Mode"
                        }
                    ]
                }
            },
            "modes": [
                {
                    "name": "Default",
                    "channels": [
                        "Lens 1",
                        "Lens 2",
                        "Lens 3",
                        "Lens 4",
                        "Lens 5",
                        "Lens 6",
                        "Lens 7",
                        "Strobe",
                        "Internal Programs, Auto Mode, Sound Controlled Mode"
                    ]
                }
            ]
        }
    ]
}